Workbook

Sheet Cover
A1: RELIANCE INDUSTRIES LIMITED
A2: Financial Valuation Report
A4: Valuation Date | B4: 46317
A5: Financial Period | B5: FY2025–26
A8: VALUATION METHODS
A9: Discounted Cash Flow (DCF)
A10: Comparable Company Valuation
A11: Sum-of-the-Parts (SOTP)
A13: KEY VALUATION OUTPUTS Equity Value (₹ crore)
A14: DCF Implied Equity Value (₹ crore) | B14: =DCF!B19 -> 716043.58
A15: SOTP Implied Equity Value (₹ crore) | B15: =SOTP_valuation!D13 -> 2077051
A17: DATA SOURCES
A18: Historical Financials Reliance Industries Limited Annual Reports, FY2021–22 to FY2025–26
A19: Segment Analysis Reliance Industries Limited Integrated Annual Report FY2025–26
A20: Comparable Companies Respective company annual reports for FY2025–26 and market-price sources on the stated valuation date
A21: Market Data Share prices and shares outstanding should be verified against dated market data and company disclosures
A23: VALUATION NOTES
A24: • DCF Assumptions Forecasts use assumed revenue growth, EBITDA margin, tax rate, capital expenditure, depreciation, working capital requirements, WACC and terminal growth.
A25: • Comparable Company Valuation EV/Revenue and EV/EBITDA multiples are calculated using market capitalisation, net debt, revenue and EBITDA.
A26: • SOTP Valuation Segment valuation multiples are illustrative assumptions and require peer-based validation.
A27: • Important Disclaimer This report is an academic and analytical valuation exercise. Forecasts and valuation outputs are estimates, not guarantees of market value or investment recommendations.

Sheet Assumptions
A1: Reliance Industries Limited | Valuation Assumptions
A3: Assumption | B3: Unit | C3: Base Case | D3: Rationale / Source
A4: Revenue Growth | B4: % | C4: 0.08 | D4: Base-case forecast assumption of 8.0%, below FY2026 actual revenue growth of approximately 9.75%; not company guidance.
A5: EBITDA Margin | B5: % | C5: 0.175 | D5: Based on FY2026 EBITDA of ₹207,911 crore divided by gross revenue of ₹1,175,919 crore, giving an actual margin of approximately 17.68%; 17.5% is the rounded forecast assumption.
A6: Tax Rate | B6: % | C6: 0.25 | D6: Provisional normalized tax-rate assumption for forecasting; not verified as Reliance’s normalized effective tax rate.
A7: Capital Expenditure | B7: % of Revenue | C7: 0.105 | D7: Based on FY2026 cash-flow-statement capex of ₹122,916 crore divided by gross revenue of ₹1,175,919 crore, approximately 10.5%. Uses the same capex measure as the historical financials; verify the precise line-item definition before finalizing.
A8: Depreciation | B8: % of Revenue | C8: 0.049 | D8: Based on FY2026 depreciation and amortisation of ₹57,688 crore divided by gross revenue of ₹1,175,919 crore, approximately 4.9%. Verify the source line-item definition before finalizing.
A9: Working Capital Change | B9: % of Revenue Growth | C9: 0.05 | D9: Provisional assumption of 5.0% of revenue growth. To be validated against historical changes in operating working capital and revenue growth before finalizing the forecast.
A10: WACC | B10: % | C10: 0.1 | D10: Initial assumption of 10.0%; validate using cost of equity, after-tax cost of debt, capital structure and market-based inputs.
A11: Terminal Growth Rate | B11: % | C11: 0.04 | D11: Long-term nominal growth assumption of 4.0%; must remain below WACC and be tested through sensitivity analysis.
A12: Forecast Period | B12: Years | C12: 5

Sheet Historical_financials
A1: Reliance Industries Limited | Historical Financial Analysis
A3: Financial Metric | B3: Unit | C3: FY2022 | D3: FY2023 | E3: FY2024 | F3: FY2025 | G3: FY2026 | H3: Source / Notes
A4: Gross Revenue | B4: ₹ crore | C4: 788743 | D4: 974864 | E4: 1000122 | F4: 1071174 | G4: 1175919 | H4: Reliance Industries Limited, Annual Reports FY2021-22 to FY2025-26, Consolidated Financial Highlights; amounts in ₹ crore.
A5: Revenue from Operations | B5: ₹ crore | C5: 717635 | D5: 891311 | E5: 914472 | F5: 980136 | G5: 1075675 | H5: Reliance Industries Limited, Annual Reports FY2021-22 to FY2025-26, consolidated revenue from operations; amounts in ₹ crore.
A6: EBITDA | B6: ₹ crore | C6: 123684 | D6: 153920 | E6: 178290 | F6: 183422 | G6: 207911 | H6: Reliance Industries Limited, Annual Reports FY2021-22 to FY2025-26, Consolidated Financial Highlights; EBITDA, ₹ crore.
A7: EBITDA Margin on Gross Revenue | B7: % | C7: =C6/C4 -> 0.15681153 | D7: =D6/D4 -> 0.15788869 | E7: =E6/E4 -> 0.17826825 | F7: =F6/F4 -> 0.17123455 | G7: =G6/G4 -> 0.17680725 | H7: Calculated as EBITDA divided by Gross Revenue for each financial year; underlying figures sourced from Reliance Industries Limited consolidated financial highlights, FY2021-22 to FY2025-26. Percentages calculated in Excel.
A8: Profit Before Tax | B8: ₹ crore | C8: 82154 | D8: 94046 | E8: 104340 | F8: 106017 | G8: 123162 | H8: Reliance Industries Limited, consolidated financial statements, Annual Reports FY2021-22 to FY2025-26; Profit Before Tax, ₹ crore. Verify the exact statement line and definition for each year.
A9: Profit After Tax | B9: ₹ crore | C9: 67845 | D9: 74088 | E9: 79020 | F9: 81309 | G9: 95754 | H9: Reliance Industries Limited, consolidated financial statements, Annual Reports FY2021-22 to FY2025-26; verify whether each figure represents profit for the year or profit attributable to owners of the parent; amounts in ₹ crore.
A10: Operating Cash Flow | B10: ₹ crore | C10: 110654 | D10: 115032 | E10: 158788 | F10: 178703 | G10: 192113 | H10: Reliance Industries Limited, consolidated statements of cash flows, Annual Reports FY2021-22 to FY2025-26; net cash generated from operating activities, ₹ crore.
A11: Capital Expenditure | B11: ₹ crore | C11: 100145 | D11: 140988 | E11: 152883 | F11: 139967 | G11: 122916 | H11: Reliance Industries Limited, consolidated statements of cash flows, Annual Reports FY2021-22 to FY2025-26; expenditure on property, plant and equipment, spectrum and other intangible assets, ₹ crore. Distinct from management-reported capex.
A12: Total Assets | B12: ₹ crore | C12: 1499665 | D12: 1607431 | E12: 1755986 | F12: 1950121 | G12: 2178140 | H12: Reliance Industries Limited, consolidated balance sheets, Annual Reports FY2021-22 to FY2025-26; total assets at each financial year-end, ₹ crore.
A13: Total Equity | B13: ₹ crore | C13: 888984 | D13: 828881 | E13: 925788 | F13: 1009626 | G13: 1085866 | H13: Reliance Industries Limited, consolidated balance sheets, Annual Reports FY2021-22 to FY2025-26; total equity at each financial year-end, ₹ crore. Verify consistency of the reported equity line across years.
A14: Gross Debt | B14: ₹ crore | C14: 266305 | D14: 313966 | E14: 324622 | F14: 347530 | G14: 374421 | H14: Reliance Industries Limited, consolidated financial statements and annual-report financial highlights, FY2021-22 to FY2025-26; gross debt at each financial year-end, ₹ crore. Verify the reported debt definition and consistency across years.
A15: Net Debt | B15: ₹ crore | C15: 34815 | D15: 125766 | E15: 116281 | F15: 117083 | G15: 124717 | H15: Reliance Industries Limited, annual reports FY2021-22 to FY2025-26; net debt at each financial year-end, ₹ crore. Verify the reported definition and consistency across years.

Sheet Segment_analysis
A1: RELIANCE INDUSTRIES LIMITED
A2: SEGMENT ANALYSIS
A4: Segment | B4: FY2026 Revenue (₹ crore) | C4: Revenue Share | D4: Business Description | E4: Source
A5: Oil-to-Chemicals | B5: 662401 | C5: =B5/$B$10 -> 0.50409769 | D5: Refining, fuels and petrochemicals | E5: Reliance Industries Annual Report FY2025-26
A6: Oil & Gas | B6: 23861 | C6: =B6/$B$10 -> 0.0181586 | D6: Oil and gas exploration and production | E6: Reliance Industries Annual Report FY2025-26
A7: Retail | B7: 371085 | C7: =B7/$B$10 -> 0.28240158 | D7: Retail stores and commerce | E7: Reliance Industries Annual Report FY2025-26
A8: Digital Services | B8: 176164 | C8: =B8/$B$10 -> 0.1340636 | D8: Telecom and digital services | E8: Reliance Industries Annual Report FY2025-26
A9: Other / Eliminations | B9: 80522 | C9: =B9/$B$10 -> 0.061278522 | D9: Other business segments | E9: Reliance Industries Annual Report FY2025-26
A10: Total | B10: =SUM(B5:B9) -> 1314033 | C10: =SUM(C5:C9) -> 1 | D10: Total segment revenue before eliminations | E10: Calculated from reported segment figures
A11: Less: Inter-segment eliminations | B11: -138114
A12: Consolidated Gross Revenue | B12: =B10+B11 -> 1175919

Sheet Forecast
A1: RELIANCE INDUSTRIES LIMITED
A2: FINANCIAL FORECAST
A4: Financial metric | B4: FY2026 Actual | C4: FY2027E | D4: FY2028E | E4: FY2029E | F4: FY2030E | G4: FY2031E
A5: Gross Revenue | B5: =Historical_financials!G4 -> 1175919 | C5: =B5*(1+Assumptions!$C$4) -> 1269992.5 | D5: =C5*(1+Assumptions!$C$4) -> 1371591.9 | E5: =D5*(1+Assumptions!$C$4) -> 1481319.3 | F5: =E5*(1+Assumptions!$C$4) -> 1599824.8 | G5: =F5*(1+Assumptions!$C$4) -> 1727810.8
A6: Revenue Growth | B6: =B5/Historical_financials!F4-1 -> 0.097785234 | C6: =C5/B5-1 -> 0.08 | D6: =D5/C5-1 -> 0.08 | E6: =E5/D5-1 -> 0.08 | F6: =F5/E5-1 -> 0.08 | G6: =G5/F5-1 -> 0.08
A7: EBITDA | B7: =Historical_financials!G6 -> 207911 | C7: =C5*Assumptions!$C$5 -> 222248.69 | D7: =D5*Assumptions!$C$5 -> 240028.59 | E7: =E5*Assumptions!$C$5 -> 259230.87 | F7: =F5*Assumptions!$C$5 -> 279969.34 | G7: =G5*Assumptions!$C$5 -> 302366.89
A8: EBITDA Margin | B8: =Historical_financials!G7 -> 0.17680725 | C8: =C7/C5 -> 0.175 | D8: =D7/D5 -> 0.175 | E8: =E7/E5 -> 0.175 | F8: =F7/F5 -> 0.175 | G8: =G7/G5 -> 0.175
A9: Depreciation & Amortisation | B9: =57688 -> 57688 | C9: =C5*Assumptions!$C$8 -> 62229.633 | D9: =D5*Assumptions!$C$8 -> 67208.004 | E9: =E5*Assumptions!$C$8 -> 72584.644 | F9: =F5*Assumptions!$C$8 -> 78391.416 | G9: =G5*Assumptions!$C$8 -> 84662.729
A10: EBIT | B10: =B7-B9 -> 150223 | C10: =C7-C9 -> 160019.06 | D10: =D7-D9 -> 172820.58 | E10: =E7-E9 -> 186646.23 | F10: =F7-F9 -> 201577.93 | G10: =G7-G9 -> 217704.16
A11: Tax on EBIT | B11: =B10*Assumptions!C6 -> 37555.75 | C11: =C10*Assumptions!$C$6 -> 40004.764 | D11: =D10*Assumptions!$C$6 -> 43205.146 | E11: =E10*Assumptions!$C$6 -> 46661.557 | F11: =F10*Assumptions!$C$6 -> 50394.482 | G11: =G10*Assumptions!$C$6 -> 54426.04
A12: NOPAT | B12: =B10-B11 -> 112667.25 | C12: =C10-C11 -> 120014.29 | D12: =D10-D11 -> 129615.44 | E12: =E10-E11 -> 139984.67 | F12: =F10-F11 -> 151183.45 | G12: =G10-G11 -> 163278.12
A13: Capital Expenditure | B13: =Historical_financials!G11 -> 122916 | C13: =C5*Assumptions!$C$7 -> 133349.21 | D13: =D5*Assumptions!$C$7 -> 144017.15 | E13: =E5*Assumptions!$C$7 -> 155538.52 | F13: =F5*Assumptions!$C$7 -> 167981.61 | G13: =G5*Assumptions!$C$7 -> 181420.13
A14: Change in Working Capital | B14: =0 -> 0 | C14: =(C5-B5)*Assumptions!$C$9 -> 4703.676 | D14: =(D5-C5)*Assumptions!$C$9 -> 5079.9701 | E14: =(E5-D5)*Assumptions!$C$9 -> 5486.3677 | F14: =(F5-E5)*Assumptions!$C$9 -> 5925.2771 | G14: =(G5-F5)*Assumptions!$C$9 -> 6399.2993
A15: Unlevered Free Cash Flow (UFCF) | B15: =B12+B9-B13-B14 -> 47439.25 | C15: =C12+C9-C13-C14 -> 44191.036 | D15: =D12+D9-D13-D14 -> 47726.319 | E15: =E12+E9-E13-E14 -> 51544.424 | F15: =F12+F9-F13-F14 -> 55667.978 | G15: =G12+G9-G13-G14 -> 60121.417

Sheet DCF
A1: RELIANCE INDUSTRIES LIMITED
A2: Discounted Cash Flow Valuation
A4: Financial Metric | B4: FY2026A | C4: FY2027E | D4: FY2028E | E4: FY2029E | F4: FY2030E | G4: FY2031E
A5: Forecast Year | C5: 1 | D5: 2 | E5: 3 | F5: 4 | G5: 5
A6: Unlevered Free Cash Flow | C6: =Forecast!C15 -> 44191.036 | D6: =Forecast!D15 -> 47726.319 | E6: =Forecast!E15 -> 51544.424 | F6: =Forecast!F15 -> 55667.978 | G6: =Forecast!G15 -> 60121.417
A7: Discount Period | C7: 1 | D7: 2 | E7: 3 | F7: 4 | G7: 5
A8: Discount Factor | C8: =1/(1+$B$11)^C7 -> 0.90909091 | D8: =1/(1+$B$11)^D7 -> 0.82644628 | E8: =1/(1+$B$11)^E7 -> 0.7513148 | F8: =1/(1+$B$11)^F7 -> 0.68301346 | G8: =1/(1+$B$11)^G7 -> 0.62092132
A9: Present Value of UFCF | C9: =C6*C8 -> 40173.669 | D9: =D6*D8 -> 39443.239 | E9: =E6*E8 -> 38726.089 | F9: =F6*F8 -> 38021.978 | G9: =G6*G8 -> 37330.67
A11: WACC | B11: 0.1
A12: Terminal Growth Rate | B12: 0.04
A14: Terminal Value | G14: =G6*(1+$B$12)/($B$11-$B$12) -> 1042104.6
A15: Present Value of Terminal Value | G15: =G14*G8 -> 647064.94
A17: Enterprise Value | B17: =SUM(C9:G9)+G15 -> 840760.58
A18: Less: Net Debt (FY2026) | B18: =Historical_financials!G15 -> 124717
A19: Equity Value | B19: =B17-B18 -> 716043.58
A22: DCF VALUATION SUMMARY
A23: Metric | B23: Value (₹ crore)
A24: Present Value of Forecast UFCF | B24: =SUM(C9:G9) -> 193695.64
A25: Present Value of Terminal Value | B25: =G15 -> 647064.94
A26: Enterprise Value | B26: =B17 -> 840760.58
A27: Less: Net Debt | B27: =B18 -> 124717
A28: Equity Value | B28: =B19 -> 716043.58
A29: Terminal Value as % of Enterprise Value | B29: =G15/B17 -> 0.76961855
A30: WACC | B30: =B11 -> 0.1
A31: Terminal Growth Rate | B31: =B12 -> 0.04
A34: DCF INTERPRETATION
A35: • The Discounted Cash Flow method estimates enterprise value by discounting projected unlevered free cash flows and terminal value at the weighted average cost of capital (WACC).
A36: • The explicit forecast period covers FY2027–FY2031.
A37: • Terminal value represents the estimated value of cash flows beyond the explicit forecast period under the perpetual growth assumption.
A38: • Equity value is calculated by subtracting FY2026 net debt from enterprise value.
A39: • The valuation is sensitive to WACC, terminal growth, revenue growth, operating margins and capital expenditure assumptions.
A40: • Forecast assumptions are illustrative and require validation against historical performance and market evidence.

Sheet Trading_comps
A2: RELIANCE INDUSTRIES LIMITED
A3: Comparable Company Valuation
A5: Metric | B5: Reliance Industries | C5: Comparable 1 | D5: Comparable 2 | E5: Comparable 3
A6: Company Name | B6: Reliance Industries | C6: Indian Oil Corporation | D6: Bharti Airtel | E6: Avenue Supermarts (DMart)
A7: Share Price (₹) | B7: 1184.5 | C7: 130.98 | D7: 1895 | E7: 3166
A8: Shares Outstanding (crore) | B8: 1353.2473 | C8: 1377.156 | D8: 580.9 | E8: 65.19
A9: Market Capitalisation (₹ crore) | B9: =B7*B8 -> 1602921.4 | C9: =C7*C8 -> 180379.89 | D9: =D7*D8 -> 1100805.5 | E9: =E7*E8 -> 206391.54
A10: Net Debt (₹ crore) | B10: =Historical_financials!G15 -> 124717 | C10: 118356.05 | D10: 107949 | E10: 1804.03
A11: Enterprise Value (₹ crore) | B11: =B9+B10 -> 1727638.4 | C11: =C9+C10 -> 298735.94 | D11: =D9+D10 -> 1208754.5 | E11: =E9+E10 -> 208195.57
A12: FY2026 Revenue (₹ crore) | B12: =Historical_financials!G4 -> 1175919 | C12: 901452.7 | D12: 210972.8 | E12: 68820.74
A13: FY2026 EBITDA (₹ crore) | B13: =Historical_financials!G6 -> 207911 | C13: 77061.65 | D13: 121267.6 | E13: 5620.69
A14: EV / Revenue (x) | B14: =B11/B12 -> 1.4691815 | C14: =C11/C12 -> 0.33139392 | D14: =D11/D12 -> 5.7294329 | E14: =E11/E12 -> 3.0251864
A15: EV / EBITDA (x) | B15: =B11/B13 -> 8.3095095 | C15: =C11/C13 -> 3.8765838 | D15: =D11/D13 -> 9.9676624 | E15: =E11/E13 -> 37.040927
A18: Comparable Company Analysis
A19: Reliance EV / Revenue | B19: =B14 -> 1.4691815
A20: Reliance EV / EBITDA | B20: =B15 -> 8.3095095
A21: Interpretatation | B21: Reliance's EV/EBITDA multiple is below those of Bharti Airtel and Avenue Supermarts in this selected peer set. Differences in business mix, growth, and accounting limit direct comparability.

Sheet SOTP_valuation
A1: RELIANCE INDUSTRIES LIMITED
A2: SUM-OF-THE-PARTS VALUATION
A4: Business Segment | B4: EV / EBITDA Multiple (x) | C4: Segment EBITDA (₹ crore) | D4: Estimated Enterprise Value (₹ crore) | E4: Source / Rationale
A5: Oil-to-Chemicals | B5: 8 | C5: 60546 | D5: =B5*C5 -> 484368 | E5: FY2026 segment EBITDA × illustrative 8.0× EV/EBITDA; multiple requires peer validation.
A6: Oil & Gas | B6: 6 | C6: 19050 | D6: =B6*C6 -> 114300 | E6: FY2026 segment EBITDA × illustrative 6.0× EV/EBITDA; multiple requires peer validation.
A7: Retail | B7: 18 | C7: 27034 | D7: =B7*C7 -> 486612 | E7: FY2026 segment EBITDA × illustrative 18.0× EV/EBITDA; multiple requires peer validation.
A8: Digital Services | B8: 12 | C8: 76560 | D8: =B8*C8 -> 918720 | E8: FY2026 segment EBITDA × illustrative 12.0× EV/EBITDA; multiple requires peer validation.
A9: Other / Unallocated (Residual) | B9: 8 | C9: 24721 | D9: =C9*B9 -> 197768 | E9: Residual EBITDA calculated as consolidated EBITDA less the four listed segment figures; requires reconciliation to the FY2025–26 annual report.
A10: Total Segment Enterprise Value | C10: =SUM(C5:C9) -> 207911 | D10: =SUM(D5:D9) -> 2201768 | E10: Sum of estimated segment enterprise values
A12: Less: Net Debt (₹ crore) | D12: =Historical_financials!G15 -> 124717 | E12: FY2026 consolidated net debt; Historical_financials!G15.
A13: Implied Equity Value (₹ crore) | D13: =D10-D12 -> 2077051 | E13: Total segment enterprise value less consolidated net debt.
A16: Note: Segment multiples are illustrative assumptions, not independently verified peer trading multiples. Residual EBITDA and segment definitions require reconciliation to the FY2025–26 annual report.

Sheet Sensitivity_checks
A1: DCF SENSITIVITY ANALYSIS
A2: Equity Value (₹ crore)
A4: WACC / Terminal Growth | B4: 0.02 | C4: 0.03 | D4: 0.04 | E4: 0.05 | F4: 0.06
A5: 0.09 | B5: {=SUMPRODUCT(DCF!$C$6:$G$6,1/(1+$A5)^DCF!$C$7:$G$7)+(DCF!$G$6*(1+B$4)/($A5-B$4))/(1+$A5)^5-DCF!$B$18} -> 643684.26 | C5: {=SUMPRODUCT(DCF!$C$6:$G$6,1/(1+$A5)^DCF!$C$7:$G$7)+(DCF!$G$6*(1+C$4)/($A5-C$4))/(1+$A5)^5-DCF!$B$18} -> 745092.66 | D5: {=SUMPRODUCT(DCF!$C$6:$G$6,1/(1+$A5)^DCF!$C$7:$G$7)+(DCF!$G$6*(1+D$4)/($A5-D$4))/(1+$A5)^5-DCF!$B$18} -> 887064.42 | E5: {=SUMPRODUCT(DCF!$C$6:$G$6,1/(1+$A5)^DCF!$C$7:$G$7)+(DCF!$G$6*(1+E$4)/($A5-E$4))/(1+$A5)^5-DCF!$B$18} -> 1100022.1 | F5: {=SUMPRODUCT(DCF!$C$6:$G$6,1/(1+$A5)^DCF!$C$7:$G$7)+(DCF!$G$6*(1+F$4)/($A5-F$4))/(1+$A5)^5-DCF!$B$18} -> 1454951.5
A6: 0.1 | B6: {=SUMPRODUCT(DCF!$C$6:$G$6,1/(1+$A6)^DCF!$C$7:$G$7)+(DCF!$G$6*(1+B$4)/($A6-B$4))/(1+$A6)^5-DCF!$B$18} -> 544944.68 | C6: {=SUMPRODUCT(DCF!$C$6:$G$6,1/(1+$A6)^DCF!$C$7:$G$7)+(DCF!$G$6*(1+C$4)/($A6-C$4))/(1+$A6)^5-DCF!$B$18} -> 618272.78 | D6: {=SUMPRODUCT(DCF!$C$6:$G$6,1/(1+$A6)^DCF!$C$7:$G$7)+(DCF!$G$6*(1+D$4)/($A6-D$4))/(1+$A6)^5-DCF!$B$18} -> 716043.58 | E6: {=SUMPRODUCT(DCF!$C$6:$G$6,1/(1+$A6)^DCF!$C$7:$G$7)+(DCF!$G$6*(1+E$4)/($A6-E$4))/(1+$A6)^5-DCF!$B$18} -> 852922.71 | F6: {=SUMPRODUCT(DCF!$C$6:$G$6,1/(1+$A6)^DCF!$C$7:$G$7)+(DCF!$G$6*(1+F$4)/($A6-F$4))/(1+$A6)^5-DCF!$B$18} -> 1058241.4
A7: 0.11 | B7: {=SUMPRODUCT(DCF!$C$6:$G$6,1/(1+$A7)^DCF!$C$7:$G$7)+(DCF!$G$6*(1+B$4)/($A7-B$4))/(1+$A7)^5-DCF!$B$18} -> 468232.22 | C7: {=SUMPRODUCT(DCF!$C$6:$G$6,1/(1+$A7)^DCF!$C$7:$G$7)+(DCF!$G$6*(1+C$4)/($A7-C$4))/(1+$A7)^5-DCF!$B$18} -> 523237.55 | D7: {=SUMPRODUCT(DCF!$C$6:$G$6,1/(1+$A7)^DCF!$C$7:$G$7)+(DCF!$G$6*(1+D$4)/($A7-D$4))/(1+$A7)^5-DCF!$B$18} -> 593958.69 | E7: {=SUMPRODUCT(DCF!$C$6:$G$6,1/(1+$A7)^DCF!$C$7:$G$7)+(DCF!$G$6*(1+E$4)/($A7-E$4))/(1+$A7)^5-DCF!$B$18} -> 688253.54 | F7: {=SUMPRODUCT(DCF!$C$6:$G$6,1/(1+$A7)^DCF!$C$7:$G$7)+(DCF!$G$6*(1+F$4)/($A7-F$4))/(1+$A7)^5-DCF!$B$18} -> 820266.34
A8: 0.12 | B8: {=SUMPRODUCT(DCF!$C$6:$G$6,1/(1+$A8)^DCF!$C$7:$G$7)+(DCF!$G$6*(1+B$4)/($A8-B$4))/(1+$A8)^5-DCF!$B$18} -> 406935.19 | C8: {=SUMPRODUCT(DCF!$C$6:$G$6,1/(1+$A8)^DCF!$C$7:$G$7)+(DCF!$G$6*(1+C$4)/($A8-C$4))/(1+$A8)^5-DCF!$B$18} -> 449388.8 | D8: {=SUMPRODUCT(DCF!$C$6:$G$6,1/(1+$A8)^DCF!$C$7:$G$7)+(DCF!$G$6*(1+D$4)/($A8-D$4))/(1+$A8)^5-DCF!$B$18} -> 502455.81 | E8: {=SUMPRODUCT(DCF!$C$6:$G$6,1/(1+$A8)^DCF!$C$7:$G$7)+(DCF!$G$6*(1+E$4)/($A8-E$4))/(1+$A8)^5-DCF!$B$18} -> 570684.82 | F8: {=SUMPRODUCT(DCF!$C$6:$G$6,1/(1+$A8)^DCF!$C$7:$G$7)+(DCF!$G$6*(1+F$4)/($A8-F$4))/(1+$A8)^5-DCF!$B$18} -> 661656.84
A9: 0.13 | B9: {=SUMPRODUCT(DCF!$C$6:$G$6,1/(1+$A9)^DCF!$C$7:$G$7)+(DCF!$G$6*(1+B$4)/($A9-B$4))/(1+$A9)^5-DCF!$B$18} -> 356846.37 | C9: {=SUMPRODUCT(DCF!$C$6:$G$6,1/(1+$A9)^DCF!$C$7:$G$7)+(DCF!$G$6*(1+C$4)/($A9-C$4))/(1+$A9)^5-DCF!$B$18} -> 390367.81 | D9: {=SUMPRODUCT(DCF!$C$6:$G$6,1/(1+$A9)^DCF!$C$7:$G$7)+(DCF!$G$6*(1+D$4)/($A9-D$4))/(1+$A9)^5-DCF!$B$18} -> 431338.47 | E9: {=SUMPRODUCT(DCF!$C$6:$G$6,1/(1+$A9)^DCF!$C$7:$G$7)+(DCF!$G$6*(1+E$4)/($A9-E$4))/(1+$A9)^5-DCF!$B$18} -> 482551.79 | F9: {=SUMPRODUCT(DCF!$C$6:$G$6,1/(1+$A9)^DCF!$C$7:$G$7)+(DCF!$G$6*(1+F$4)/($A9-F$4))/(1+$A9)^5-DCF!$B$18} -> 548397.49
